passlib/__init__.py
passlib/_data/wordsets/bip39.txt
passlib/_data/wordsets/eff_long.txt
passlib/_data/wordsets/eff_prefixed.txt
passlib/_data/wordsets/eff_short.txt
passlib/_setup/__init__.py
passlib/_setup/stamp.py
passlib/apache.py
passlib/apps.py
passlib/context.py
passlib/crypto/__init__.py
passlib/crypto/_blowfish/__init__.py
passlib/crypto/_blowfish/_gen_files.py
passlib/crypto/_blowfish/base.py
passlib/crypto/_blowfish/unrolled.py
passlib/crypto/_md4.py
passlib/crypto/des.py
passlib/crypto/digest.py
passlib/crypto/scrypt/__init__.py
passlib/crypto/scrypt/_builtin.py
passlib/crypto/scrypt/_gen_files.py
passlib/crypto/scrypt/_salsa.py
passlib/exc.py
passlib/ext/__init__.py
passlib/ext/django/__init__.py
passlib/ext/django/models.py
passlib/ext/django/utils.py
passlib/handlers/__init__.py
passlib/handlers/argon2.py
passlib/handlers/bcrypt.py
passlib/handlers/cisco.py
passlib/handlers/des_crypt.py
passlib/handlers/digests.py
passlib/handlers/django.py
passlib/handlers/fshp.py
passlib/handlers/ldap_digests.py
passlib/handlers/md5_crypt.py
passlib/handlers/misc.py
passlib/handlers/mssql.py
passlib/handlers/mysql.py
passlib/handlers/oracle.py
passlib/handlers/pbkdf2.py
passlib/handlers/phpass.py
passlib/handlers/postgres.py
passlib/handlers/roundup.py
passlib/handlers/scram.py
passlib/handlers/scrypt.py
passlib/handlers/sha1_crypt.py
passlib/handlers/sha2_crypt.py
passlib/handlers/sun_md5_crypt.py
passlib/handlers/windows.py
passlib/hash.py
passlib/hosts.py
passlib/ifc.py
passlib/pwd.py
passlib/registry.py
passlib/tests/__init__.py
passlib/tests/__main__.py
passlib/tests/_test_bad_register.py
passlib/tests/backports.py
passlib/tests/sample1.cfg
passlib/tests/sample1b.cfg
passlib/tests/sample1c.cfg
passlib/tests/sample_config_1s.cfg
passlib/tests/test_apache.py
passlib/tests/test_apps.py
passlib/tests/test_context.py
passlib/tests/test_context_deprecated.py
passlib/tests/test_crypto_builtin_md4.py
passlib/tests/test_crypto_des.py
passlib/tests/test_crypto_digest.py
passlib_fork-1.7.4.post1.dist-info/METADATA
passlib_fork-1.7.4.post1.dist-info/WHEEL
passlib_fork-1.7.4.post1.dist-info/licenses/LICENSE
passlib_fork-1.7.4.post1.dist-info/RECORD
